csv_to_json/__init__.py
csv_to_json/csv_to_json.py
csv_to_json-0.0.5.dist-info/LICENSE
csv_to_json-0.0.5.dist-info/METADATA
csv_to_json-0.0.5.dist-info/WHEEL
csv_to_json-0.0.5.dist-info/top_level.txt
csv_to_json-0.0.5.dist-info/RECORD
