Metadata-Version: 2.1
Name: csv-to-json
Version: 0.0.5
Summary: A simple csv to json coverter
Home-page: https://github.com/Ruturaj4/csv_to_json
Author: ruturaj4
Author-email: ruturajkvaidya@gmail.com
License: UNKNOWN
Platform: UNKNOWN
Classifier: Programming Language :: Python :: 3
Classifier: License :: OSI Approved :: MIT License
Classifier: Operating System :: OS Independent
Requires-Dist: setuptools (>=39.2.0)
Requires-Dist: pandas (>=0.23.4)
